gitlab_api_helper/__init__.py
gitlab_api_helper/api_helper.py
gitlab_api_helper/cmd.py
gitlab_api_helper-1.0.1.dist-info/licenses/LICENSE
gitlab_api_helper-1.0.1.dist-info/METADATA
gitlab_api_helper-1.0.1.dist-info/WHEEL
gitlab_api_helper-1.0.1.dist-info/entry_points.txt
gitlab_api_helper-1.0.1.dist-info/top_level.txt
gitlab_api_helper-1.0.1.dist-info/RECORD
