Metadata-Version: 2.4
Name: gitlab-api-helper
Version: 1.0.1
Summary: A simple tool that calls gitlab api to generate the repo summary
Home-page: https://github.com/changyy/gitlab-api-helper
Download-URL: https://pypi.org/project/gitlab-api-helper/
Author: Yuan-Yi Chang
Author-email: <changyy.csie@gmail.com>
Keywords: python,gitlab,api,report,summary
Classifier: Programming Language :: Python :: 3
Classifier: Operating System :: MacOS :: MacOS X
Requires-Python: >=3.10
License-File: LICENSE
Requires-Dist: pandas
Dynamic: author
Dynamic: author-email
Dynamic: classifier
Dynamic: description
Dynamic: description-content-type
Dynamic: download-url
Dynamic: home-page
Dynamic: keywords
Dynamic: license-file
Dynamic: requires-dist
Dynamic: requires-python
Dynamic: summary
